tudan/__init__.py
tudan-0.0.1.dist-info/METADATA
tudan-0.0.1.dist-info/WHEEL
tudan-0.0.1.dist-info/entry_points.txt
tudan-0.0.1.dist-info/top_level.txt
tudan-0.0.1.dist-info/RECORD
