Metadata-Version: 2.1
Name: tudan
Version: 0.0.1
Summary: Toolkit for infra management
Home-page: https://github.com/WorkshopHQ/tudan
Author: Tan Li
Author-email: tan@tanli.dev
Project-URL: Bug Tracker, https://github.com/WorkshopHQ/tudan/issues
Project-URL: Changelog, https://github.com/WorkshopHQ/tudan/releases
Classifier: Programming Language :: Python :: 3
Classifier: License :: OSI Approved :: Apache Software License
Classifier: Operating System :: OS Independent
Requires-Python: >=3.8
Requires-Dist: rich
Requires-Dist: textual
Requires-Dist: typer
Requires-Dist: termcolor
Requires-Dist: tiktoken
Requires-Dist: faiss-cpu
Requires-Dist: openai
Requires-Dist: lancedb
Requires-Dist: guidance
Requires-Dist: supabase
Requires-Dist: unstructured[local-inference]
Provides-Extra: dev
Requires-Dist: black ; extra == 'dev'
Requires-Dist: Faker ; extra == 'dev'
Requires-Dist: flake8 ; extra == 'dev'
Requires-Dist: isort ; extra == 'dev'
Requires-Dist: memray ; extra == 'dev'
Requires-Dist: pdbpp ; extra == 'dev'
Requires-Dist: pytest ; extra == 'dev'
Requires-Dist: richbench ; extra == 'dev'
Requires-Dist: python-dotenv ; extra == 'dev'
